[{"Image":"image\/1.jpg","Name":"Alexander Frederik Rasmus Binger","Phone":"60400036","Gender":"Male"},{"Image":"image\/2.jpg","Name":"Alexander Philip Sekj\u00e6r","Phone":"60107776","Gender":"Male"},{"Image":"image\/3.jpg","Name":"Alexander Rasmussen","Phone":"","Gender":"Male"},{"Image":"image\/4.jpg","Name":"Alexandra Pedersen ","Phone":"+4550722964","Gender":"Female"},{"Image":"image\/5.jpg","Name":"Anders Donde ","Phone":"+4520414544","Gender":"Male"},{"Image":"image\/6.jpg","Name":"Andreas Vilhelm Kvist","Phone":"28939078","Gender":"Male"},{"Image":"image\/7.jpg","Name":"Ane Helmer","Phone":"26810760","Gender":"Female"},{"Image":"image\/8.jpg","Name":"Angelo Pozzato","Phone":"60107809","Gender":"Male"},{"Image":"image\/9.jpg","Name":"Ann Christina B\u00e6kdahl","Phone":"60107816","Gender":"Female"},{"Image":"image\/10.jpg","Name":"Ann Marzella Schwartz","Phone":"+4560107786","Gender":"Female"},{"Image":"image\/11.jpg","Name":"Anne Kirstine Lindemann M\u00f8ller","Phone":"60107818","Gender":"Female"},{"Image":"image\/12.jpg","Name":"Anne Louise Clausen","Phone":"60200608","Gender":"Female"},{"Image":"image\/13.jpg","Name":"Anne Marie Stougaard","Phone":"60107759","Gender":"Female"},{"Image":"image\/14.jpg","Name":"Anne Sophie Vendal","Phone":"+4560107768","Gender":"Female"},{"Image":"image\/15.jpg","Name":"Bas Meister","Phone":"60107796","Gender":"Male"},{"Image":"image\/16.jpg","Name":"Camilla Dragsted ","Phone":"+4560107801","Gender":"Female"},{"Image":"image\/17.jpg","Name":"Camilla Nordvig","Phone":"26155019","Gender":"Female"},{"Image":"image\/18.jpg","Name":"Charlotte Esmann","Phone":"+4560107756","Gender":"Female"},{"Image":"image\/19.jpg","Name":"Christian Pedersen","Phone":"60200610","Gender":"Male"},{"Image":"image\/20.jpg","Name":"Christian Toft Rasmussen","Phone":"60200600","Gender":"Male"},{"Image":"image\/21.jpg","Name":"Clara Therese Prior-Knock","Phone":"60200605","Gender":"Female"},{"Image":"image\/22.jpg","Name":"Claudia Rodas","Phone":"+4560107790","Gender":"Female"},{"Image":"image\/23.jpg","Name":"Claus Collstrup","Phone":"+4560107795","Gender":"Male"},{"Image":"image\/24.jpg","Name":"Daniel Simon","Phone":"+4541833575","Gender":"Male"},{"Image":"image\/25.jpg","Name":"Elias Nikos Vakirtzis  Poulsen","Phone":"60374828","Gender":"Male"},{"Image":"image\/26.jpg","Name":"Emilie Brandt","Phone":"+4527280607","Gender":"Female"},{"Image":"image\/27.jpg","Name":"Esben Amtorp","Phone":"60107783","Gender":"Male"},{"Image":"image\/28.jpg","Name":"Frederik Salling Troels-Smith","Phone":"22439085","Gender":"Male"},{"Image":"image\/29.jpg","Name":"Frederik Stensballe Halby ","Phone":"+4560107798","Gender":"Male"},{"Image":"image\/30.jpg","Name":"Hanne Thorsgaard ","Phone":"60200609","Gender":"Female"},{"Image":"image\/31.jpg","Name":"Henriette Keyper","Phone":"60107808","Gender":"Female"},{"Image":"image\/32.jpg","Name":"Henrik Seeward","Phone":"60107788","Gender":"Male"},{"Image":"image\/33.jpg","Name":"Henrik Snoer ","Phone":"60107806","Gender":"Male"},{"Image":"image\/34.jpg","Name":"Henrik Tvilling","Phone":"+4560405500","Gender":"Male"},{"Image":"image\/35.jpg","Name":"Ingerlise Maasb\u00f8l ","Phone":"+4560374846","Gender":"Female"},{"Image":"image\/36.jpg","Name":"Jabali Ravn","Phone":"+4560107750","Gender":"Male"},{"Image":"image\/37.jpg","Name":"Jacob Benzon Malmmose","Phone":"60374829","Gender":"Male"},{"Image":"image\/38.jpg","Name":"Jannie Buhrkall Tychsen","Phone":"60107792","Gender":"Male"},{"Image":"image\/39.jpg","Name":"Jeanne Schultz","Phone":"60374845","Gender":"Female"},{"Image":"image\/40.jpg","Name":"Jens Peter Jensen","Phone":"+4560374848","Gender":"Male"},{"Image":"image\/41.jpg","Name":"Jesper J\u00f8rgensen","Phone":"+4560374823","Gender":"Male"},{"Image":"image\/42.jpg","Name":"Jonas Kring Surrow","Phone":"60107784","Gender":"Male"},{"Image":"image\/43.jpg","Name":"Jonas M\u00f8rkeby","Phone":"60107789","Gender":"Male"},{"Image":"image\/44.jpg","Name":"Jonas Sylvest ","Phone":"+4560400032","Gender":"Male"},{"Image":"image\/45.jpg","Name":"Josephine Irmelin Gram Ludvigsen","Phone":"60107815","Gender":"Female"},{"Image":"image\/46.jpg","Name":"Judith K\u00f6thnig","Phone":"60200604","Gender":"Female"},{"Image":"image\/47.jpg","Name":"Julie Elander Pehrsson","Phone":"+4560107755","Gender":"Female"},{"Image":"image\/48.jpg","Name":"Karl Alexander Veng ","Phone":"+4560107782","Gender":"Male"},{"Image":"image\/49.jpg","Name":"Karl Kristian Krarup Kj\u00e6r","Phone":"23639555","Gender":"Male"},{"Image":"image\/50.jpg","Name":"Karsten L. Flindt","Phone":"31105020","Gender":"Male"},{"Image":"image\/51.jpg","Name":"Kasper Kabbeltved Pedersen","Phone":"+4560107793","Gender":"Male"},{"Image":"image\/52.jpg","Name":"Katrine Berling ","Phone":"+4560374825","Gender":"Female"},{"Image":"image\/53.jpg","Name":"Katrine Ringsing ","Phone":"+4560107762","Gender":"Female"},{"Image":"image\/54.jpg","Name":"Kenneth Dederding Espensen","Phone":"+4560107761","Gender":"Male"},{"Image":"image\/55.jpg","Name":"Kenneth M\u00f8ller","Phone":"+4560107760","Gender":"Male"},{"Image":"image\/56.jpg","Name":"Kitta Petersen","Phone":"60107812","Gender":"Female"},{"Image":"image\/57.jpg","Name":"Kristel Kr\u00f8ier","Phone":"+4542144618","Gender":"Female"},{"Image":"image\/58.jpg","Name":"Kristina Naasunnguaq Jensen ","Phone":"60107805","Gender":"Female"},{"Image":"image\/59.jpg","Name":"Lasse Elg\u00e5rd Vintersb\u00f8lle ","Phone":"+4560107764","Gender":"Male"},{"Image":"image\/60.jpg","Name":"Lasse Jakobsen","Phone":"+4560107797","Gender":"Male"},{"Image":"image\/61.jpg","Name":"Lea Krag Fogh ","Phone":"+4560374821","Gender":"Female"},{"Image":"image\/62.jpg","Name":"Leander Tram","Phone":"25629494","Gender":"Male"},{"Image":"image\/63.jpg","Name":"Lene Skjoldborg Gaarde ","Phone":"+4560107754","Gender":"Female"},{"Image":"image\/64.jpg","Name":"Linette Vendelbo Pedersen","Phone":"","Gender":"Female"},{"Image":"image\/65.jpg","Name":"Lisa Beith Fischer","Phone":"+4560107771","Gender":"Female"},{"Image":"image\/66.jpg","Name":"Lotte Jakobsen","Phone":"+4560107766","Gender":"Female"},{"Image":"image\/67.jpg","Name":"Luong Lu","Phone":"60107767\/+46704001551","Gender":"Male"},{"Image":"image\/68.jpg","Name":"Maja Arabi","Phone":"20637912","Gender":"Female"},{"Image":"image\/69.jpg","Name":"Maja Hartmann","Phone":"+4560107774","Gender":"Female"},{"Image":"image\/70.jpg","Name":"Maria Agerbo Kofoed","Phone":"60107813","Gender":"Female"},{"Image":"image\/71.jpg","Name":"Marianne Hjaltelin","Phone":"+4560107765","Gender":"Female"},{"Image":"image\/72.jpg","Name":"Marie Amalie Stenholt B\u00f8ckel","Phone":"60374827","Gender":"Female"},{"Image":"image\/73.jpg","Name":"Marie Bonnesen ","Phone":"+4560107781","Gender":"Female"},{"Image":"image\/74.jpg","Name":"Marlene Schou","Phone":"+4560374839","Gender":"Female"},{"Image":"image\/75.jpg","Name":"Massimo Fiorentino","Phone":"29259246","Gender":"Male"},{"Image":"image\/76.jpg","Name":"Mats Siiger Eiers\u00f8","Phone":"+4560107802","Gender":"Male"},{"Image":"image\/77.jpg","Name":"Mette B\u00e6kby Bertelsen","Phone":"60200607","Gender":"Female"},{"Image":"image\/78.jpg","Name":"Mette H\u00f8rdum","Phone":"+4521844004","Gender":"Female"},{"Image":"image\/79.jpg","Name":"Mette Riis Kruse ","Phone":"+4560107794","Gender":"Female"},{"Image":"image\/80.jpg","Name":"Mia Pichard Ertner","Phone":"60107811","Gender":"Female"},{"Image":"image\/81.jpg","Name":"Michael Kowal","Phone":"60107810","Gender":"Male"},{"Image":"image\/82.jpg","Name":"Michael Nih\u00f8j Rasmussen ","Phone":"+4560374820","Gender":"Male"},{"Image":"image\/83.jpg","Name":"Michael Venneberg ","Phone":"+4560107799","Gender":"Male"},{"Image":"image\/84.jpg","Name":"Mikkel Emil Lindgaard ","Phone":"60107817","Gender":"Male"},{"Image":"image\/85.jpg","Name":"Mikkel Jerichau","Phone":"23325919","Gender":"Male"},{"Image":"image\/86.jpg","Name":"Mikkel S\u00f8borg","Phone":"26225541","Gender":"Male"},{"Image":"image\/87.jpg","Name":"Morten Bak ","Phone":"+4525379717","Gender":"Male"},{"Image":"image\/88.jpg","Name":"Morten Fjelsted","Phone":"40963002","Gender":"Male"},{"Image":"image\/89.jpg","Name":"Mounia Bensalem","Phone":"60107819","Gender":"Female"},{"Image":"image\/90.jpg","Name":"Natalia Alexandra Szwebs ","Phone":"22112602","Gender":"Female"},{"Image":"image\/91.jpg","Name":"Nicolai Dimon","Phone":"29252998","Gender":"Male"},{"Image":"image\/92.jpg","Name":"Nicolai Stahl","Phone":"+4560107777","Gender":"Male"},{"Image":"image\/93.jpg","Name":"Niels Heilberg","Phone":"+4560374833","Gender":"Male"},{"Image":"image\/94.jpg","Name":"Niklas Myschetzky","Phone":"","Gender":"Male"},{"Image":"image\/95.jpg","Name":"Nina Lisa Johansen","Phone":"60200606","Gender":"Female"},{"Image":"image\/96.jpg","Name":"Nusha Haghighi","Phone":"60107814","Gender":"Female"},{"Image":"image\/97.jpg","Name":"P\u00e5l \u00d8sterud","Phone":"+4530201075","Gender":"Male"},{"Image":"image\/98.jpg","Name":"Pernille Str\u00f8m Lundsfryd ","Phone":"+4560374843","Gender":"Female"},{"Image":"image\/99.jpg","Name":"Pernille Warneke","Phone":"+4560107780","Gender":"Female"},{"Image":"image\/100.jpg","Name":"Peter Porsmose","Phone":"60200602","Gender":"Male"},{"Image":"image\/101.jpg","Name":"Peter Theglev","Phone":"+4540830472","Gender":"Male"},{"Image":"image\/102.jpg","Name":"Pia J\u00f8nsson","Phone":"+4560374849","Gender":"Female"},{"Image":"image\/103.jpg","Name":"Ragnhild Sofie Arnbj\u00f8rn Lemmeke","Phone":"28598062","Gender":"Female"},{"Image":"image\/104.jpg","Name":"Rasmus Bidstrup","Phone":"+4560400660","Gender":"Male"},{"Image":"image\/105.jpg","Name":"Rasmus Gottliebsen","Phone":"+4560107757","Gender":"Male"},{"Image":"image\/106.jpg","Name":"Receptionen","Phone":"+4533137090","Gender":"Male"},{"Image":"image\/107.jpg","Name":"Rose Hallingskov","Phone":"60400037","Gender":"Female"},{"Image":"image\/108.jpg","Name":"Sabine H\u00f8jrup Hansen","Phone":"60107773","Gender":"Female"},{"Image":"image\/109.jpg","Name":"Sandra Amalie Lacoppidan","Phone":"60107807","Gender":"Female"},{"Image":"image\/110.jpg","Name":"Sarah Backer","Phone":"60374826","Gender":"Female"},{"Image":"image\/111.jpg","Name":"Sarita Montenegro","Phone":"+4560374824","Gender":"Female"},{"Image":"image\/112.jpg","Name":"Sidsel Birkedal Fuglsang","Phone":"51887462","Gender":"Female"},{"Image":"image\/113.jpg","Name":"Signe Marie Vilhelmsen","Phone":"60107753","Gender":"Female"},{"Image":"image\/114.jpg","Name":"Signe M\u00f8ller","Phone":"60107803","Gender":"Female"},{"Image":"image\/115.jpg","Name":"Sine Carlsen ","Phone":"+4560107804","Gender":"Female"},{"Image":"image\/116.jpg","Name":"Softcom","Phone":"70226464","Gender":"Male"},{"Image":"image\/117.jpg","Name":"Steffen V. Hjaltelin ","Phone":"+4560107770","Gender":"Male"},{"Image":"image\/118.jpg","Name":"Stina Buchhave","Phone":"+4531909160","Gender":"Female"},{"Image":"image\/119.jpg","Name":"Stine Gregersen","Phone":"+4560374835","Gender":"Female"},{"Image":"image\/120.jpg","Name":"Sus Mandrup Hansen","Phone":"+4560107751","Gender":"Female"},{"Image":"image\/121.jpg","Name":"S\u00f8ren Allerup","Phone":"20450950","Gender":"Male"},{"Image":"image\/122.jpg","Name":"S\u00f8ren Gr\u00f8nborg","Phone":"+4560107800","Gender":"Male"},{"Image":"image\/123.jpg","Name":"Taxa (Dantaxi)","Phone":"38790850","Gender":"Taxa"},{"Image":"image\/124.jpg","Name":"Theis Clausen","Phone":"","Gender":"Male"},{"Image":"image\/125.jpg","Name":"Thilde Egvang","Phone":"60107788","Gender":"Female"},{"Image":"image\/126.jpg","Name":"Thomas Adamsen ","Phone":"+4526303515","Gender":"Male"},{"Image":"image\/127.jpg","Name":"Thomas Bach ","Phone":"+4551888747","Gender":"Male"},{"Image":"image\/128.jpg","Name":"Tobias Smidth-Fibiger","Phone":"+4560374840","Gender":"Male"},{"Image":"image\/129.jpg","Name":"Trine de Florie (p\u00e5 barsel)","Phone":"+4560107769","Gender":"Female"},{"Image":"image\/130.jpg","Name":"Trine Petersen ","Phone":"+4560107763","Gender":"Female"},{"Image":"image\/131.jpg","Name":"Ulla Snetoft \u00d8dum","Phone":"60374832","Gender":"Female"},{"Image":"image\/132.jpg","Name":"Ulrik Michelsen","Phone":"+4560107778","Gender":"Male"},{"Image":"image\/133.jpg","Name":"Vibeke Stisen (Vibse)","Phone":"+4522511881","Gender":"Female"},{"Image":"image\/134.jpg","Name":"Yong Bautista","Phone":"+4560400667","Gender":"Male"}]